scrapy_ext/__init__.py
scrapy_ext/ua_list.py
scrapy_ext/downloadermiddlewares/useragent.py
scrapy_ext-0.0.2.dist-info/METADATA
scrapy_ext-0.0.2.dist-info/RECORD
scrapy_ext-0.0.2.dist-info/WHEEL
scrapy_ext-0.0.2.dist-info/top_level.txt
