Metadata-Version: 2.1
Name: scrapy-ext
Version: 0.0.2
Summary: Useful Scrapy extensions
Home-page: https://creatiweb.cz
Author: Vitek Pliska
Author-email: vitek@creatiweb.cz
License: UNKNOWN
Platform: UNKNOWN
